postalservice/__init__.py
postalservice/utils/__init__.py
postalservice/utils/network_utils.py
postalservice/utils/search_utils.py
postalservice-0.2.0.dist-info/licenses/LICENSE
tests/__init__.py
tests/test_services.py
postalservice-0.2.0.dist-info/METADATA
postalservice-0.2.0.dist-info/WHEEL
postalservice-0.2.0.dist-info/top_level.txt
postalservice-0.2.0.dist-info/RECORD
