Metadata-Version: 2.4
Name: postalservice
Version: 0.2.0
Summary: A package for second hand shopping
Author: Aapo Montin
License-File: LICENSE
Dynamic: author
Dynamic: description
Dynamic: description-content-type
Dynamic: license-file
Dynamic: summary
